README.md
setup.py
faire_api_client/__init__.py
faire_api_client/client.py
faire_api_client/config.py
faire_api_client/resources.py
faire_api_client/utils.py
faire_api_client.egg-info/PKG-INFO
faire_api_client.egg-info/SOURCES.txt
faire_api_client.egg-info/dependency_links.txt
faire_api_client.egg-info/top_level.txt