Metadata-Version: 2.1
Name: faire-api-client
Version: 0.0.1
Summary: A simple api client for FAIRE plateform
Home-page: https://github.com/sathouel/faire_api_client
Author: Steven Athouel
Author-email: sathouel@gmail.com
License: UNKNOWN
Platform: UNKNOWN
Classifier: Programming Language :: Python :: 3
Classifier: License :: OSI Approved :: MIT License
Classifier: Operating System :: OS Independent
Requires-Python: >=3.6
